FoolPyWebView/FoolCom.js
FoolPyWebView/FoolJsComps.py
FoolPyWebView/FoolPyWebView.py
FoolPyWebView/__init__.py
FoolPyWebView/qwebchannel.js
FoolPyWebView-1.5.0.dist-info/METADATA
FoolPyWebView-1.5.0.dist-info/WHEEL
FoolPyWebView-1.5.0.dist-info/top_level.txt
FoolPyWebView-1.5.0.dist-info/RECORD
